hpcrocket/__init__.py
hpcrocket/__main__.py
hpcrocket/cli/__init__.py
hpcrocket/cli/_builders.py
hpcrocket/cli/_parsers.py
hpcrocket/cli/_yaml.py
hpcrocket/core/__init__.py
hpcrocket/core/application.py
hpcrocket/core/errors.py
hpcrocket/core/executor.py
hpcrocket/core/filesystem/__init__.py
hpcrocket/core/filesystem/_filesystem.py
hpcrocket/core/filesystem/glob.py
hpcrocket/core/filesystem/progressive.py
hpcrocket/core/launchoptions.py
hpcrocket/core/slurmbatchjob.py
hpcrocket/core/slurmcontroller.py
hpcrocket/core/workflowfactory.py
hpcrocket/core/workflows/__init__.py
hpcrocket/core/workflows/stages.py
hpcrocket/core/workflows/workflow.py
hpcrocket/pyfilesystem/__init__.py
hpcrocket/pyfilesystem/factory.py
hpcrocket/pyfilesystem/localfilesystem.py
hpcrocket/pyfilesystem/pyfilesystembased.py
hpcrocket/pyfilesystem/sshfilesystem.py
hpcrocket/ssh/__init__.py
hpcrocket/ssh/chmodsshfs.py
hpcrocket/ssh/connectiondata.py
hpcrocket/ssh/errors.py
hpcrocket/ssh/sshexecutor.py
hpcrocket/typesafety.py
hpcrocket/ui.py
hpcrocket/watcher/__init__.py
hpcrocket/watcher/jobwatcher.py
hpcrocket/watcher/watcherthread.py
test/__init__.py
test/acceptance/test_launch_acceptance.py
test/application/__init__.py
test/application/assertions.py
test/application/executor_filesystem_callorder.py
test/application/optionbuilders.py
test/application/test_application_cancel_options.py
test/application/test_application_cancel_watching.py
test/application/test_application_collect_clean.py
test/application/test_application_finalize_options.py
test/application/test_application_launch_options.py
test/application/test_application_status_options.py
test/application/test_application_watch_options.py
test/integration/__init__.py
test/integration/application/fixtures.py
test/integration/application/test_application_with_filesystem.py
test/integration/application/test_application_with_paramiko.py
test/integration/cli/__init__.py
test/integration/cli/test_cli_app_integration.py
hpc_rocket-0.6.3.dist-info/entry_points.txt
hpc_rocket-0.6.3.dist-info/WHEEL
hpc_rocket-0.6.3.dist-info/METADATA
hpc_rocket-0.6.3.dist-info/licenses/LICENSE
hpc_rocket-0.6.3.dist-info/licenses/AUTHORS
hpc_rocket-0.6.3.dist-info/RECORD
