Metadata-Version: 2.1
Name: hpc-rocket
Version: 0.6.3
Summary: A tool to run Slurm sbatch commands over SSH
License: MIT
Author-email: Sven Marcus <s.marcus@outlook.de>
Requires-Python: >=3.9
Classifier: Development Status :: 4 - Beta
Classifier: Environment :: Console
Classifier: Intended Audience :: Science/Research
Classifier: License :: OSI Approved :: MIT License
Classifier: Programming Language :: Python :: 3
Classifier: Programming Language :: Python :: 3.10
Classifier: Programming Language :: Python :: 3.11
Classifier: Programming Language :: Python :: 3.12
Classifier: Programming Language :: Python :: 3.13
Classifier: Programming Language :: Python :: 3.9
Requires-Dist: PyYAML>=5.4.1
Requires-Dist: cffi==1.17
Requires-Dist: fs-sshfs>=1.0.1
Requires-Dist: fs>=2.4.16
Requires-Dist: paramiko>=2.10.4
Requires-Dist: rich>=10.1.0
Requires-Dist: typing-extensions==4.14
